LICENSE
MANIFEST.in
README.md
setup.py
metalsmyth/__init__.py
metalsmyth.egg-info/PKG-INFO
metalsmyth.egg-info/SOURCES.txt
metalsmyth.egg-info/dependency_links.txt
metalsmyth.egg-info/not-zip-safe
metalsmyth.egg-info/requires.txt
metalsmyth.egg-info/top_level.txt
metalsmyth/plugins/__init__.py
metalsmyth/plugins/dates.py
metalsmyth/plugins/drafts.py
metalsmyth/plugins/markup.py
metalsmyth/plugins/template.py
tests/dates/hello.markdown
tests/dates/network-diagrams.markdown
tests/drafts/hello.markdown
tests/drafts/network-diagrams.markdown
tests/markup/ebola.md
tests/markup/network-diagrams.md
tests/markup/responsive-d3.md
tests/markup/template.md
tests/noop/hello.markdown
tests/noop/network-diagrams.markdown
tests/templates/post.html