Metadata-Version: 1.0
Name: metalsmyth
Version: 0.1.4
Summary: Process a directory of files with frontmatter and middleware
Home-page: https://github.com/eyeseast/python-metalsmyth
Author: Chris Amico
Author-email: eyeseast@gmail.com
License: MIT
Keywords: frontmatter static-generator
Platform: UNKNOWN
Classifier: Development Status :: 2 - Pre-Alpha
Classifier: Intended Audience :: Developers
Classifier: License :: OSI Approved :: MIT License
Classifier: Natural Language :: English
Classifier: Programming Language :: Python :: 2
Classifier: Programming Language :: Python :: 2.6
Classifier: Programming Language :: Python :: 2.7
Classifier: Programming Language :: Python :: 3
Classifier: Programming Language :: Python :: 3.3
Classifier: Programming Language :: Python :: 3.4
